pyproject.toml
setup.py
expro/expro.f90
expro/expro_pycomm.f90
expro/expro_util.f90
geo/geo.f90
pygacode/__init__.py
pygacode/gacodefuncs.py
pygacode/gacodeinput.py
pygacode.egg-info/PKG-INFO
pygacode.egg-info/SOURCES.txt
pygacode.egg-info/dependency_links.txt
pygacode.egg-info/top_level.txt
pygacode/cgyro/__init__.py
pygacode/cgyro/conv_gs2.py
pygacode/cgyro/data.py
pygacode/cgyro/data_distill.py
pygacode/cgyro/data_dump.py
pygacode/cgyro/data_plot.py
pygacode/cgyro/data_plot_single.py
pygacode/cgyro/plot_fluct.py
pygacode/cgyro/plot_rt.py
pygacode/cgyro/plot_template.py
pygacode/cgyro/vis_supertorus.py
pygacode/cgyro/vis_torcut.py
pygacode/cgyro/vis_wheel.py
pygacode/gyro/__init__.py
pygacode/gyro/data.py
pygacode/gyro/data_plot.py
pygacode/gyro/data_plot_single.py
pygacode/gyro/fluctuation2d.py
pygacode/gyro/text_flux.py
pygacode/neo/__init__.py
pygacode/neo/data.py
pygacode/neo/errorcheck.py
pygacode/neo/flux.py
pygacode/neo/interpreter.py
pygacode/neo/options.py
pygacode/profiles_gen/__init__.py
pygacode/profiles_gen/plot_locpargen_geo.py
pygacode/profiles_gen/plot_profile.py
pygacode/profiles_gen/plot_surf.py
pygacode/profiles_gen/prgen_contour.py
pygacode/profiles_gen/prgen_geqdsk.py
pygacode/profiles_gen/prgen_shape.py
pygacode/profiles_gen/prgen_shapeprofile.py
pygacode/test/__init__.py
pygacode/test/input.gacode
pygacode/test/test_install.py
pygacode/tgyro/__init__.py
pygacode/tgyro/data.py
pygacode/tgyro/plot_notebook.py