Metadata-Version: 2.1
Name: pygacode
Version: 1.0.0
Summary: Python-GACODE
License: MIT
Project-URL: Homepage, https://gacode.io
Requires-Python: >=3.8
